rubetek_socket_api/__init__.py
rubetek_socket_api/exceptions.py
rubetek_socket_api/logger.py
rubetek_socket_api/models.py
rubetek_socket_api/wrapper.py
rubetek_socket_api-0.2.3.dist-info/licenses/LICENSE
rubetek_socket_api-0.2.3.dist-info/METADATA
rubetek_socket_api-0.2.3.dist-info/WHEEL
rubetek_socket_api-0.2.3.dist-info/top_level.txt
rubetek_socket_api-0.2.3.dist-info/RECORD
