Metadata-Version: 2.4
Name: rubetek_socket_api
Version: 0.2.3
Summary: API wrapper for controlling the Rubetek RE-3305 smart socket.
Author-email: regenara <jakebv.22@gmail.com>
License: MIT License
Project-URL: repository, https://github.com/regenara/rubetek_socket_api
Project-URL: homepage, https://github.com/regenara/rubetek_socket_api
License-File: LICENSE
Requires-Dist: certifi>=2022.0.0
Requires-Dist: pydantic<3.0.0,>=2.0.0
Requires-Dist: aiohttp<4.0.0,>=3.0.0
Dynamic: license-file
